{"api-client_camera_cinematic.md":"dcc86188","api-client_camera_ped.md":"dccca690","api-client_data_atms.md":"12454c4e","api-client_data_vehicles.md":"a21201e0","api-client_data_vendingmachines.md":"9fe12338","api-client_events_keybinds.md":"f7d20267","api-client_events_keyheld.md":"57232df5","api-client_intro.md":"379a9c6a","api-client_rmlui_inputbox.md":"f1f7b7cc","api-client_rmlui_menu.md":"124a4414","api-client_rmlui_menu3d.md":"a383b2b7","api-client_rmlui_progressbar.md":"e79d0d1e","api-client_rmlui_questionbox.md":"abd5a933","api-client_rmlui_sprite.md":"a2443852","api-client_rmlui_statictext.md":"6a0f3e17","api-client_screen_drawmarker.md":"d5e2533f","api-client_screen_drawrectangle2d.md":"e615f237","api-client_screen_drawrectangle3d.md":"1457f74f","api-client_screen_drawtext2d.md":"faecfb82","api-client_screen_drawtext3d.md":"f3b8b0f3","api-client_screen_notification.md":"9e20b198","api-client_sound_frontend.md":"d1912b81","api-client_sound_play2d.md":"5ccb4676","api-client_sound_play3d.md":"bfb6d424","api-client_sound_playfromentity.md":"3ad73df3","api-client_utility_distance2d.md":"7ab7b68a","api-client_utility_distance3d.md":"8e280cea","api-client_utility_loadanimation.md":"5bb97fbd","api-client_utility_loadmodel.md":"7947d343","api-client_webview_close.md":"47483e4e","api-client_webview_emit.md":"2b68d7d6","api-client_webview_focus.md":"74443c5f","api-client_webview_isanymenuopen.md":"dbec4456","api-client_webview_on.md":"47912d1b","api-client_webview_open.md":"24c0419e","api-client_webview_openasoverlay.md":"ba58b0bc","api-client_webview_openaspersistent.md":"bfdc08d0","api-client_webview_page.md":"e3438180","api-client_webview_ready.md":"dd243bfa","api-client_webview_showcursor.md":"e0870bfc","api-client_webview_showoverlays.md":"986af417","api-client_webview_unfocus.md":"c01e1d69","api-client_wheelmenus_iwheeloption.md":"d6d11f71","api-client_wheelmenus_object.md":"8ff05c27","api-client_wheelmenus_ped.md":"382b6cbf","api-client_wheelmenus_player.md":"968411d3","api-client_wheelmenus_vehicle.md":"bf8e9232","api-server_controllers_admin.md":"8397ecf4","api-server_controllers_blip.md":"1110ca6d","api-server_controllers_chat.md":"dd9c225b","api-server_controllers_interaction.md":"abc970bf","api-server_controllers_marker.md":"293d434f","api-server_controllers_notification.md":"f65c1d13","api-server_controllers_object.md":"db80f854","api-server_controllers_ped.md":"0375f926","api-server_controllers_text.md":"657a7975","api-server_database_collections.md":"160ede5d","api-server_database_createcollection.md":"79773fd1","api-server_database_fetchallbyfield.md":"00d401e8","api-server_database_fetchalldata.md":"bea75957","api-server_database_fetchdata.md":"3e26a2ba","api-server_database_init.md":"6464f607","api-server_database_insertdata.md":"2710c381","api-server_events_player.md":"047d5123","api-server_events_vehicle.md":"23b8c805","api-server_get_player.md":"fba9cd25","api-server_get_players.md":"8f027d1b","api-server_get_vehicle.md":"95846b3c","api-server_get_vehicles.md":"8a19a51d","api-server_get_world.md":"09d16975","api-server_intro.md":"2b607c29","api-server_systems_effects.md":"6e078483","api-server_systems_identifier.md":"1f1d065e","api-server_systems_job.md":"69a3c385","api-server_systems_plugins.md":"03dd0f6c","api-server_systems_sound.md":"c5b170bb","api-server_systems_world.md":"dbb27fa2","api-server_utility_deepcloneobject.md":"048dc5d8","api-server_utility_hash.md":"041a270b","api-server_utility_isflagenabled.md":"b88c374d","api-server_utility_vector.md":"1820ed38","api-server_webview_emit.md":"94d40b2a","index.md":"9f4ed0cf","intro_how-do-i_access-a-player-by-id.md":"824eab62","intro_how-do-i_become-an-admin.md":"1e188a47","intro_how-do-i_contribute.md":"10f9e9f6","intro_how-do-i_keep-my-repo-updated.md":"ab0bd7a1","intro_how-do-i_make-a-command.md":"5db6a7a8","intro_info_faq.md":"d70b016e","intro_info_folder-structure.md":"f85c18d4","intro_info_troubleshooting.md":"9e3aeb20","intro_info_using-vscode.md":"d723327a","intro_install_installing-on-linux.md":"1fe220cf","intro_install_installing-on-windows.md":"d1285415","intro_install_staying-up-to-date.md":"b8b07a4a","intro_intro_best-server-for-you.md":"57228186","intro_intro_index.md":"d5fac487","intro_intro_previews.md":"da64ef04","intro_mods_about-mods.md":"508a5093","intro_mods_adding-clothes.md":"8870cf18","intro_mods_adding-mods.md":"5493353f","intro_mods_adding-vehicles.md":"de24fb0e","plugins_about-plugins.md":"7bc96772","plugins_atm_atm.md":"6b56cf88","plugins_atm_locales.md":"74b44c87","plugins_character-creator_character-creator.md":"10f97a7b","plugins_character-creator_locales.md":"761d4883","plugins_character-select_character-select.md":"42d15e7f","plugins_character-select_locales.md":"46d357d0","plugins_clothing_clothing.md":"ad171455","plugins_clothing_locales.md":"603e88d8","plugins_commands_client-commands.md":"9fc01859","plugins_commands_cmds-chat.md":"4dc74c21","plugins_commands_cmds-job.md":"500ac1d1","plugins_commands_cmds-mod-chat.md":"b62785e7","plugins_commands_cmds-mod-currency.md":"a2161a06","plugins_commands_cmds-mod-garage.md":"f49d99b5","plugins_commands_cmds-mod-interior.md":"d2f75b2b","plugins_commands_cmds-mod-inventory.md":"f7d487bb","plugins_commands_cmds-mod-noclip.md":"82570079","plugins_commands_cmds-mod-player.md":"746f8969","plugins_commands_cmds-mod-teleport.md":"286c6e77","plugins_commands_cmds-mod-testing.md":"ec25a619","plugins_commands_cmds-mod-vehicle.md":"e0a78a74","plugins_commands_cmds-mod-weapon.md":"cd3da465","plugins_commands_cmds-vehicle.md":"d11549ae","plugins_commands_commands.md":"eca921cd","plugins_commands_server-commands.md":"7725efa1","plugins_creating-plugins.md":"c7253c77","plugins_cuffs_cuffs.md":"7f2b3ad1","plugins_dealership_dealership.md":"ee5ff118","plugins_dealership_locales.md":"e9fbc973","plugins_death_death.md":"541926f0","plugins_discord_discord.md":"32f3162b","plugins_factions-paychecks_factions-paychecks.md":"7f67930f","plugins_factions_config-about.md":"6a35a6f5","plugins_factions_config-vehicles.md":"88de0ebb","plugins_factions_config-webview-injections.md":"e586b836","plugins_factions_factions.md":"0d20a8be","plugins_factions_features.md":"6f1d5d79","plugins_factions_locales.md":"76ed1450","plugins_fuel-station_fuel-station.md":"2dc129b0","plugins_fuel-station_locales.md":"9df8de27","plugins_fuel_fuel.md":"28109e05","plugins_fuel_locales.md":"e870e5eb","plugins_garage_garage.md":"93d7c5ef","plugins_garage_locales.md":"46ca4bbb","plugins_loading-plugins.md":"a03c552c","plugins_voice_voice.md":"efe7d1dc","tools_toolkit.md":"3d03c714","user-plugins_index.md":"d606b675","user-plugins_readmes_booster1212_open-source-shop.md":"057e49f9","user-plugins_readmes_booster1212_plugin-attachmenteditor.md":"5e6efddf","user-plugins_readmes_booster1212_plugin-farmingsystem.md":"24abd2c6","user-plugins_readmes_dexslab_rolelife-faction-docs.md":"b8812c0a","user-plugins_readmes_itsspencer_athena-plugin-doorlocker.md":"887bc4b0","user-plugins_readmes_itsspencer_athena-plugin-tackling.md":"138f5b9c","user-plugins_readmes_jonasesser_gp-flatbed.md":"f2a1c223","user-plugins_readmes_jonasesser_gp-interiors.md":"f51c4bc9","user-plugins_readmes_jonasesser_gp-portal.md":"4886e8eb","user-plugins_readmes_jonasesser_gp-shop.md":"0ca2c716","user-plugins_readmes_jonasesser_gp-voice-demophone.md":"8ba04cdc","user-plugins_readmes_locutus1119_athena-plugin-omega-actions.md":"6ce11433","user-plugins_readmes_locutus1119_athena-plugin-omega-homeless.md":"e6f2a6d0","user-plugins_readmes_locutus1119_athena-plugin-omega-player-list.md":"71042825","user-plugins_readmes_locutus1119_athena-plugin-omega-vehicle-rental.md":"0a196a3c","user-plugins_readmes_mcwulf1991_even-more-jobs.md":"3c44fde6","user-plugins_readmes_mcwulf1991_plugin-core-tuningshop.md":"1c3ae182","user-plugins_readmes_shakirplayz_job-activate-power.md":"c82c7874","user-plugins_readmes_stuyk_altv-athena-plugin-template.md":"0eea3427","user-plugins_terms-of-use.md":"629a13af"}
